README.md
setup.py
ops_channel/__init__.py
ops_channel/base.py
ops_channel/test.py
ops_channel.egg-info/PKG-INFO
ops_channel.egg-info/SOURCES.txt
ops_channel.egg-info/dependency_links.txt
ops_channel.egg-info/top_level.txt