Metadata-Version: 2.2
Name: ops_channel
Version: 0.6.2
Summary: ops_channel util
Home-page: https://github.com/sjqzhang/ops_channel
Author: jqzhang
Author-email: s_jqzhang@163.com
License: MIT Licence
Keywords: pip,ops_channel
Platform: any
Dynamic: author
Dynamic: author-email
Dynamic: description
Dynamic: home-page
Dynamic: keywords
Dynamic: license
Dynamic: platform
Dynamic: summary
